README.md
setup.py
needl/api_handler.py
needl/get_entries.py
needl.egg-info/PKG-INFO
needl.egg-info/SOURCES.txt
needl.egg-info/dependency_links.txt
needl.egg-info/requires.txt
needl.egg-info/top_level.txt
needl/objects/candidateset.py
needl/objects/dataset.py
needl/objects/gene.py
needl/objects/ontology.py
needl/objects/organism.py
needl/objects/run.py
needl/objects/score.py
needl/objects/tissue.py
needl/objects/variant.py